docs/mrxcavator.html
mrxcavator.py
mrxcavator-0.6.3.dist-info/entry_points.txt
mrxcavator-0.6.3.dist-info/LICENSE
mrxcavator-0.6.3.dist-info/WHEEL
mrxcavator-0.6.3.dist-info/METADATA
mrxcavator-0.6.3.dist-info/RECORD
