Metadata-Version: 2.1
Name: mrxcavator
Version: 0.6.3
Summary: CLI client for CRXcavator.io
Home-page: https://github.com/mstanislav/mrxcavator
License: MIT
Author: Mark Stanislav
Author-email: mark.stanislav@gmail.com
Requires-Python: >=3.6.1,<4.0.0
Classifier: License :: OSI Approved :: MIT License
Classifier: Programming Language :: Python :: 3
Classifier: Programming Language :: Python :: 3.7
Classifier: Programming Language :: Python :: 3.8
Classifier: Programming Language :: Python :: 3.9
Requires-Dist: PyInquirer (==1.0.3)
Requires-Dist: asciichartpy (==1.5.21)
Requires-Dist: packaging (>=20.9,<21.0)
Requires-Dist: requests (>=2.24.0,<3.0.0)
Requires-Dist: termtables (>=0.2.2,<0.3.0)
Requires-Dist: tqdm (>=4.48.0,<5.0.0)
Requires-Dist: validators (>=0.16.0,<0.17.0)
Project-URL: Documentation, https://mstanislav.github.io/mrxcavator/mrxcavator.html
Project-URL: Repository, https://github.com/mstanislav/mrxcavator
